{"metadata":{},"options":{"compact":false,"sourceMaps":true,"ast":true,"babelrc":false,"configFile":false,"parserOpts":{"sourceType":"module","sourceFileName":"/home/michal-pc/Dokumenty/CubeMaster/client/imports/components/training/index.js","plugins":["*","flow","jsx","asyncGenerators","bigInt","classPrivateMethods","classPrivateProperties","classProperties","doExpressions","dynamicImport","exportDefaultFrom","exportExtensions","exportNamespaceFrom","functionBind","functionSent","importMeta","nullishCoalescingOperator","numericSeparator","objectRestSpread","optionalCatchBinding","optionalChaining",["pipelineOperator",{"proposal":"minimal"}],"throwExpressions","classProperties","classPrivateProperties","jsx",["flow",{}],"nullishCoalescingOperator","nullishCoalescingOperator","optionalChaining","optionalChaining","optionalCatchBinding","optionalCatchBinding","classProperties","classPrivateProperties","classPrivateMethods","classProperties","classPrivateProperties","asyncGenerators","asyncGenerators","objectRestSpread","objectRestSpread",["flow",{}]],"allowImportExportEverywhere":true,"allowReturnOutsideFunction":true,"allowUndeclaredExports":true,"strictMode":false},"caller":{"name":"meteor","arch":"web.browser"},"sourceFileName":"client/imports/components/training/index.js","filename":"/home/michal-pc/Dokumenty/CubeMaster/client/imports/components/training/index.js","passPerPreset":false,"envName":"development","cwd":"/home/michal-pc/Dokumenty/CubeMaster","root":"/home/michal-pc/Dokumenty/CubeMaster","plugins":[{"key":"base$0","visitor":{"_exploded":true,"_verified":true},"options":{}},{"key":"base$0$0","visitor":{"Program":{"enter":[null],"exit":[null]},"_exploded":true,"_verified":true},"options":{"avoidModernSyntax":false,"enforceStrictMode":false,"dynamicImport":true,"generateLetDeclarations":true}},{"key":"transform-runtime","visitor":{"CallExpression":{"enter":[null]},"BinaryExpression":{"enter":[null]},"MemberExpression":{"enter":[null],"exit":[null]},"_exploded":true,"_verified":true,"Identifier":{"enter":[null]},"JSXIdentifier":{"enter":[null]}},"options":{"version":"7.7.1","helpers":true,"useESModules":false,"corejs":false}},{"key":"proposal-class-properties","visitor":{"PrivateName":{"enter":[null]},"ExportDefaultDeclaration":{"enter":[null]},"_exploded":true,"_verified":true,"ClassDeclaration":{"enter":[null]},"ClassExpression":{"enter":[null]}},"options":{"loose":true}},{"key":"transform-react-jsx","visitor":{"_exploded":{},"_verified":{},"JSXNamespacedName":{"enter":[null]},"JSXSpreadChild":{"enter":[null]},"JSXElement":{"exit":[null]},"JSXFragment":{"exit":[null]},"Program":{"enter":[null],"exit":[null]},"JSXAttribute":{"enter":[null]}},"options":{"pragma":"React.createElement","pragmaFrag":"React.Fragment","throwIfNamespace":true,"useBuiltIns":false}},{"key":"transform-react-display-name","visitor":{"ExportDefaultDeclaration":{"enter":[null]},"CallExpression":{"enter":[null]},"_exploded":true,"_verified":true},"options":{}},{"key":"syntax-flow","visitor":{"_exploded":true,"_verified":true},"options":{}},{"key":"syntax-nullish-coalescing-operator","visitor":{"_exploded":true,"_verified":true},"options":{}},{"key":"proposal-nullish-coalescing-operator","visitor":{"_exploded":{},"_verified":{},"LogicalExpression":{"enter":[null]}},"options":{}},{"key":"syntax-optional-chaining","visitor":{"_exploded":true,"_verified":true},"options":{}},{"key":"proposal-optional-chaining","visitor":{"_exploded":{},"_verified":{},"OptionalCallExpression":{"enter":[null]},"OptionalMemberExpression":{"enter":[null]}},"options":{}},{"key":"syntax-optional-catch-binding","visitor":{"_exploded":true,"_verified":true},"options":{}},{"key":"proposal-optional-catch-binding","visitor":{"_exploded":{},"_verified":{},"CatchClause":{"enter":[null]}},"options":{}},{"key":"syntax-class-properties","visitor":{"_exploded":true,"_verified":true},"options":{}},{"key":"proposal-class-properties","visitor":{"PrivateName":{"enter":[null]},"ExportDefaultDeclaration":{"enter":[null]},"_exploded":true,"_verified":true,"ClassDeclaration":{"enter":[null]},"ClassExpression":{"enter":[null]}},"options":{}},{"key":"syntax-async-generators","visitor":{"_exploded":true,"_verified":true},"options":{}},{"key":"proposal-async-generator-functions","visitor":{"_exploded":{},"_verified":{},"Program":{"enter":[null]}},"options":{}},{"key":"syntax-object-rest-spread","visitor":{"_exploded":true,"_verified":true},"options":{}},{"key":"proposal-object-rest-spread","visitor":{"_exploded":{},"_verified":{},"VariableDeclarator":{"enter":[null]},"ExportNamedDeclaration":{"enter":[null]},"CatchClause":{"enter":[null]},"AssignmentExpression":{"enter":[null]},"ArrayPattern":{"enter":[null]},"ObjectExpression":{"enter":[null]},"FunctionDeclaration":{"enter":[null]},"FunctionExpression":{"enter":[null]},"ObjectMethod":{"enter":[null]},"ArrowFunctionExpression":{"enter":[null]},"ClassMethod":{"enter":[null]},"ClassPrivateMethod":{"enter":[null]},"ForInStatement":{"enter":[null]},"ForOfStatement":{"enter":[null]}},"options":{}},{"key":"transform-literals","visitor":{"NumericLiteral":{"enter":[null]},"StringLiteral":{"enter":[null]},"_exploded":true,"_verified":true},"options":{}},{"key":"transform-template-literals","visitor":{"TaggedTemplateExpression":{"enter":[null]},"TemplateLiteral":{"enter":[null]},"_exploded":true,"_verified":true},"options":{}},{"key":"transform-parameters","visitor":{"_exploded":true,"_verified":true,"FunctionDeclaration":{"enter":[null]},"FunctionExpression":{"enter":[null]},"ObjectMethod":{"enter":[null]},"ArrowFunctionExpression":{"enter":[null]},"ClassMethod":{"enter":[null]},"ClassPrivateMethod":{"enter":[null]}},"options":{}},{"key":"transform-flow-strip-types","visitor":{"_exploded":{},"_verified":{},"Program":{"enter":[null]},"ImportDeclaration":{"enter":[null,null]},"ClassProperty":{"enter":[null]},"ClassPrivateProperty":{"enter":[null]},"AssignmentPattern":{"enter":[null]},"TypeCastExpression":{"enter":[null,null]},"CallExpression":{"enter":[null]},"OptionalCallExpression":{"enter":[null]},"NewExpression":{"enter":[null]},"ImportSpecifier":{"enter":[null]},"ClassDeclaration":{"enter":[null]},"ClassExpression":{"enter":[null]},"FunctionDeclaration":{"enter":[null]},"FunctionExpression":{"enter":[null]},"ObjectMethod":{"enter":[null]},"ArrowFunctionExpression":{"enter":[null]},"ClassMethod":{"enter":[null]},"ClassPrivateMethod":{"enter":[null]},"AnyTypeAnnotation":{"enter":[null]},"ArrayTypeAnnotation":{"enter":[null]},"BooleanTypeAnnotation":{"enter":[null]},"BooleanLiteralTypeAnnotation":{"enter":[null]},"NullLiteralTypeAnnotation":{"enter":[null]},"ClassImplements":{"enter":[null]},"DeclareClass":{"enter":[null]},"DeclareFunction":{"enter":[null]},"DeclareInterface":{"enter":[null]},"DeclareModule":{"enter":[null]},"DeclareModuleExports":{"enter":[null]},"DeclareTypeAlias":{"enter":[null]},"DeclareOpaqueType":{"enter":[null]},"DeclareVariable":{"enter":[null]},"DeclareExportDeclaration":{"enter":[null]},"DeclareExportAllDeclaration":{"enter":[null]},"DeclaredPredicate":{"enter":[null]},"ExistsTypeAnnotation":{"enter":[null]},"FunctionTypeAnnotation":{"enter":[null]},"FunctionTypeParam":{"enter":[null]},"GenericTypeAnnotation":{"enter":[null]},"InferredPredicate":{"enter":[null]},"InterfaceExtends":{"enter":[null]},"InterfaceDeclaration":{"enter":[null]},"InterfaceTypeAnnotation":{"enter":[null]},"IntersectionTypeAnnotation":{"enter":[null]},"MixedTypeAnnotation":{"enter":[null]},"EmptyTypeAnnotation":{"enter":[null]},"NullableTypeAnnotation":{"enter":[null]},"NumberLiteralTypeAnnotation":{"enter":[null]},"NumberTypeAnnotation":{"enter":[null]},"ObjectTypeAnnotation":{"enter":[null]},"ObjectTypeInternalSlot":{"enter":[null]},"ObjectTypeCallProperty":{"enter":[null]},"ObjectTypeIndexer":{"enter":[null]},"ObjectTypeProperty":{"enter":[null]},"ObjectTypeSpreadProperty":{"enter":[null]},"OpaqueType":{"enter":[null]},"QualifiedTypeIdentifier":{"enter":[null]},"StringLiteralTypeAnnotation":{"enter":[null]},"StringTypeAnnotation":{"enter":[null]},"ThisTypeAnnotation":{"enter":[null]},"TupleTypeAnnotation":{"enter":[null]},"TypeofTypeAnnotation":{"enter":[null]},"TypeAlias":{"enter":[null]},"TypeAnnotation":{"enter":[null]},"TypeParameter":{"enter":[null]},"TypeParameterDeclaration":{"enter":[null]},"TypeParameterInstantiation":{"enter":[null]},"UnionTypeAnnotation":{"enter":[null]},"Variance":{"enter":[null]},"VoidTypeAnnotation":{"enter":[null]},"ExportAllDeclaration":{"enter":[null]},"ExportDefaultDeclaration":{"enter":[null]},"ExportNamedDeclaration":{"enter":[null]}},"options":{}},{"key":"transform-exponentiation-operator","visitor":{"AssignmentExpression":{"enter":[null]},"BinaryExpression":{"enter":[null]},"_exploded":true,"_verified":true},"options":{}}],"presets":[],"generatorOpts":{"filename":"/home/michal-pc/Dokumenty/CubeMaster/client/imports/components/training/index.js","comments":true,"compact":false,"sourceMaps":true,"sourceFileName":"client/imports/components/training/index.js"}},"code":"let Meteor;\nmodule.link(\"meteor/meteor\", {\n  Meteor(v) {\n    Meteor = v;\n  }\n\n}, 0);\nlet Algorithms;\nmodule.link(\"../../../../collections/algorithms\", {\n  Algorithms(v) {\n    Algorithms = v;\n  }\n\n}, 1);\nlet Results;\nmodule.link(\"../../../../collections/results\", {\n  Results(v) {\n    Results = v;\n  }\n\n}, 2);\nlet composer;\nmodule.link(\"../../lib/composer\", {\n  composer(v) {\n    composer = v;\n  }\n\n}, 3);\nlet Training;\nmodule.link(\"./training\", {\n  default(v) {\n    Training = v;\n  }\n\n}, 4);\n// TODO to be moved\nconst categories = [{\n  label: 'OLL',\n  value: 'OLL',\n  randomizableAlgorithm: true\n}, {\n  label: 'PLL',\n  value: 'PLL',\n  randomizableAlgorithm: true\n}, {\n  label: '3x3x3',\n  value: '3x3x3',\n  randomizableScramble: true\n}, {\n  label: 'OLL Attack',\n  value: 'OLL-attack',\n  algorithmsCategory: 'OLL',\n  settingsDisabled: true\n}, {\n  label: 'PLL Attack',\n  value: 'PLL-attack',\n  algorithmsCategory: 'PLL',\n  settingsDisabled: true\n}];\n\nconst compose = (props, onData) => {\n  const subscriptions = [Meteor.subscribe('algorithms'), Meteor.subscribe('results')];\n\n  if (subscriptions.every(subscription => subscription.ready())) {\n    const algorithms = Algorithms.find({}).fetch();\n    const results = Results.find({}).fetch();\n    results.forEach(result => {\n      const algorithm = algorithms.find(alg => alg._id === result.algorithmId);\n      const category = categories.find(cat => cat.value === result.category);\n\n      if (algorithm) {\n        algorithm.results = (algorithm.results || []).concat(result.time);\n      }\n\n      if (category) {\n        category.results = (category.results || []).concat(result.time);\n      }\n    });\n    onData(null, {\n      algorithms,\n      categories\n    });\n  }\n};\n\nmodule.exportDefault(composer(compose)(Training));","map":{"version":3,"sources":["client/imports/components/training/index.js"],"names":["Meteor","module","link","v","Algorithms","Results","composer","Training","default","categories","label","value","randomizableAlgorithm","randomizableScramble","algorithmsCategory","settingsDisabled","compose","props","onData","subscriptions","subscribe","every","subscription","ready","algorithms","find","fetch","results","forEach","result","algorithm","alg","_id","algorithmId","category","cat","concat","time","exportDefault"],"mappings":"AAAA,IAAIA,MAAJ;AAAWC,MAAM,CAACC,IAAP,CAAY,eAAZ,EAA4B;AAACF,EAAAA,MAAM,CAACG,CAAD,EAAG;AAACH,IAAAA,MAAM,GAACG,CAAP;AAAS;;AAApB,CAA5B,EAAkD,CAAlD;AAAqD,IAAIC,UAAJ;AAAeH,MAAM,CAACC,IAAP,CAAY,oCAAZ,EAAiD;AAACE,EAAAA,UAAU,CAACD,CAAD,EAAG;AAACC,IAAAA,UAAU,GAACD,CAAX;AAAa;;AAA5B,CAAjD,EAA+E,CAA/E;AAAkF,IAAIE,OAAJ;AAAYJ,MAAM,CAACC,IAAP,CAAY,iCAAZ,EAA8C;AAACG,EAAAA,OAAO,CAACF,CAAD,EAAG;AAACE,IAAAA,OAAO,GAACF,CAAR;AAAU;;AAAtB,CAA9C,EAAsE,CAAtE;AAAyE,IAAIG,QAAJ;AAAaL,MAAM,CAACC,IAAP,CAAY,oBAAZ,EAAiC;AAACI,EAAAA,QAAQ,CAACH,CAAD,EAAG;AAACG,IAAAA,QAAQ,GAACH,CAAT;AAAW;;AAAxB,CAAjC,EAA2D,CAA3D;AAA8D,IAAII,QAAJ;AAAaN,MAAM,CAACC,IAAP,CAAY,YAAZ,EAAyB;AAACM,EAAAA,OAAO,CAACL,CAAD,EAAG;AAACI,IAAAA,QAAQ,GAACJ,CAAT;AAAW;;AAAvB,CAAzB,EAAkD,CAAlD;AAO9U;AACA,MAAMM,UAAU,GAAG,CACjB;AACEC,EAAAA,KAAK,EAAE,KADT;AAEEC,EAAAA,KAAK,EAAE,KAFT;AAGEC,EAAAA,qBAAqB,EAAE;AAHzB,CADiB,EAMjB;AACEF,EAAAA,KAAK,EAAE,KADT;AAEEC,EAAAA,KAAK,EAAE,KAFT;AAGEC,EAAAA,qBAAqB,EAAE;AAHzB,CANiB,EAWjB;AACEF,EAAAA,KAAK,EAAE,OADT;AAEEC,EAAAA,KAAK,EAAE,OAFT;AAGEE,EAAAA,oBAAoB,EAAE;AAHxB,CAXiB,EAgBjB;AACEH,EAAAA,KAAK,EAAE,YADT;AAEEC,EAAAA,KAAK,EAAE,YAFT;AAGEG,EAAAA,kBAAkB,EAAE,KAHtB;AAIEC,EAAAA,gBAAgB,EAAE;AAJpB,CAhBiB,EAsBjB;AACEL,EAAAA,KAAK,EAAE,YADT;AAEEC,EAAAA,KAAK,EAAE,YAFT;AAGEG,EAAAA,kBAAkB,EAAE,KAHtB;AAIEC,EAAAA,gBAAgB,EAAE;AAJpB,CAtBiB,CAAnB;;AA8BA,MAAMC,OAAO,GAAG,CAACC,KAAD,EAAQC,MAAR,KAAmB;AACjC,QAAMC,aAAa,GAAG,CACpBnB,MAAM,CAACoB,SAAP,CAAiB,YAAjB,CADoB,EAEpBpB,MAAM,CAACoB,SAAP,CAAiB,SAAjB,CAFoB,CAAtB;;AAKA,MAAID,aAAa,CAACE,KAAd,CAAoBC,YAAY,IAAIA,YAAY,CAACC,KAAb,EAApC,CAAJ,EAA+D;AAC7D,UAAMC,UAAU,GAAGpB,UAAU,CAACqB,IAAX,CAAgB,EAAhB,EAAoBC,KAApB,EAAnB;AACA,UAAMC,OAAO,GAAGtB,OAAO,CAACoB,IAAR,CAAa,EAAb,EAAiBC,KAAjB,EAAhB;AAEAC,IAAAA,OAAO,CAACC,OAAR,CAAgBC,MAAM,IAAI;AACxB,YAAMC,SAAS,GAAGN,UAAU,CAACC,IAAX,CAAgBM,GAAG,IAAIA,GAAG,CAACC,GAAJ,KAAYH,MAAM,CAACI,WAA1C,CAAlB;AACA,YAAMC,QAAQ,GAAGzB,UAAU,CAACgB,IAAX,CAAgBU,GAAG,IAAIA,GAAG,CAACxB,KAAJ,KAAckB,MAAM,CAACK,QAA5C,CAAjB;;AACA,UAAIJ,SAAJ,EAAe;AACbA,QAAAA,SAAS,CAACH,OAAV,GAAoB,CAACG,SAAS,CAACH,OAAV,IAAqB,EAAtB,EAA0BS,MAA1B,CAAiCP,MAAM,CAACQ,IAAxC,CAApB;AACD;;AACD,UAAIH,QAAJ,EAAc;AACZA,QAAAA,QAAQ,CAACP,OAAT,GAAmB,CAACO,QAAQ,CAACP,OAAT,IAAoB,EAArB,EAAyBS,MAAzB,CAAgCP,MAAM,CAACQ,IAAvC,CAAnB;AACD;AACF,KATD;AAWAnB,IAAAA,MAAM,CAAC,IAAD,EAAO;AAAEM,MAAAA,UAAF;AAAcf,MAAAA;AAAd,KAAP,CAAN;AACD;AACF,CAvBD;;AAtCAR,MAAM,CAACqC,aAAP,CA+DehC,QAAQ,CAACU,OAAD,CAAR,CAAkBT,QAAlB,CA/Df","sourcesContent":["import { Meteor } from 'meteor/meteor';\n\nimport { Algorithms } from '../../../../collections/algorithms';\nimport { Results } from '../../../../collections/results';\nimport { composer } from '../../lib/composer';\nimport Training from './training';\n\n// TODO to be moved\nconst categories = [\n  {\n    label: 'OLL',\n    value: 'OLL',\n    randomizableAlgorithm: true\n  },\n  {\n    label: 'PLL',\n    value: 'PLL',\n    randomizableAlgorithm: true\n  },\n  {\n    label: '3x3x3',\n    value: '3x3x3',\n    randomizableScramble: true\n  },\n  {\n    label: 'OLL Attack',\n    value: 'OLL-attack',\n    algorithmsCategory: 'OLL',\n    settingsDisabled: true\n  },\n  {\n    label: 'PLL Attack',\n    value: 'PLL-attack',\n    algorithmsCategory: 'PLL',\n    settingsDisabled: true\n  }\n];\n\nconst compose = (props, onData) => {\n  const subscriptions = [\n    Meteor.subscribe('algorithms'),\n    Meteor.subscribe('results')\n  ];\n\n  if (subscriptions.every(subscription => subscription.ready())) {\n    const algorithms = Algorithms.find({}).fetch();\n    const results = Results.find({}).fetch();\n\n    results.forEach(result => {\n      const algorithm = algorithms.find(alg => alg._id === result.algorithmId);\n      const category = categories.find(cat => cat.value === result.category);\n      if (algorithm) {\n        algorithm.results = (algorithm.results || []).concat(result.time);\n      }\n      if (category) {\n        category.results = (category.results || []).concat(result.time);\n      }\n    });\n\n    onData(null, { algorithms, categories });\n  }\n};\n\nexport default composer(compose)(Training);\n"]},"sourceType":"module","hash":"c5765e9165545669194055100e186c2275a9ced9"}
